MANIFEST.in
README
REQUIREMENTS
dubbel.py
ez_setup.py
setup.py
dubbel.egg-info/PKG-INFO
dubbel.egg-info/SOURCES.txt
dubbel.egg-info/dependency_links.txt
dubbel.egg-info/requires.txt
dubbel.egg-info/top_level.txt
tests/run.py
tests/test_01_basic.rst
tests/test_02_additional.rst
tests/test_03_subsections.rst
tests/test_04_recursive_subsections.rst
tests/test_05_defaults.rst
tests/test_06_interpolation.rst
tests/test_07_strict_yaml.rst
tests/test_08_nested_interpolation.rst
tests/examples/interpolation.yaml
tests/examples/interpolation_nested.yaml
tests/examples/root_level_defaults.yaml
tests/examples/strict_yaml.yaml
tests/examples/test.yaml
tests/examples/with_subsections.yaml
tests/examples/with_subsubsections.yaml