Metadata-Version: 1.0
Name: dubbel
Version: 0.8.2
Summary: ConfigParser/YAML hybrid
Home-page: http://wefft.codebasehq.com/python/dubbel
Author: Walter Wefft
Author-email: contact@worrp.com
License: BSD
Download-URL: http://pypi.python.org/packages/source/d/dubbel/dubbel-0.8.2.tar.gz
Platform: UNKNOWN
Classifier: Development Status :: 4 - Beta
Classifier: Intended Audience :: Developers
Classifier: License :: OSI Approved :: BSD License
Classifier: Programming Language :: Python
Classifier: Topic :: Software Development :: Libraries
Classifier: Topic :: Software Development :: Libraries :: Python Modules
